chemispy/__init__.py
chemispy/elements/hydrogen.py
chemispy/elements/lithium.py
chemispy/elements/potassium.py
chemispy/elements/sodium.py
chemispy/utils/atomic_number_query.py
chemispy-1.1.2.dist-info/METADATA
chemispy-1.1.2.dist-info/WHEEL
chemispy-1.1.2.dist-info/top_level.txt
chemispy-1.1.2.dist-info/RECORD
