Metadata-Version: 2.1
Name: chemispy
Version: 1.1.2
Summary: A library for using chemistry in python
Home-page: https://github.com/TechPenguineer/chemispy
Author: TechPenguineer
Author-email: techpenguineer@gmail.com
License: MIT
Platform: UNKNOWN
Classifier: License :: OSI Approved :: MIT License
Classifier: Programming Language :: Python :: 3
Classifier: Programming Language :: Python :: 3.7
Requires-Dist: PyQt5
